pypigit_version.py
setup.py
pypigit_version.egg-info/PKG-INFO
pypigit_version.egg-info/SOURCES.txt
pypigit_version.egg-info/dependency_links.txt
pypigit_version.egg-info/entry_points.txt
pypigit_version.egg-info/not-zip-safe
pypigit_version.egg-info/top_level.txt