Metadata-Version: 1.1
Name: pypigit-version
Version: 0.1.10
Summary: Automatically set package version from Git.
Home-page: https://github.com/anthill-utils/pypigit-version
Author: desertkun
Author-email: desertkun@gmail.com
License: http://opensource.org/licenses/MIT
Platform: UNKNOWN
Classifier: Framework :: Setuptools Plugin
Classifier: Intended Audience :: Developers
Classifier: Programming Language :: Python
